ipython_cells/__init__.py
ipython_cells/ipython_cells.py
ipython_cells/version.py
ipython_cells-5.1.dist-info/METADATA
ipython_cells-5.1.dist-info/WHEEL
ipython_cells-5.1.dist-info/top_level.txt
ipython_cells-5.1.dist-info/RECORD
