Metadata-Version: 2.1
Name: ipython-cells
Version: 5.1
Summary: Jupyter-like cell running in ipython
Home-page: https://github.com/uiuc-sine/ipython-cells
Author: Evan Widloski, Ulaş Kamacι
Author-email: evan@evanw.org, ukamaci2@illinois.edu
License: GPLv3
Keywords: jupyter ipython cells magic extension
Platform: UNKNOWN
Classifier: Programming Language :: Python :: 3
Requires-Dist: IPython
